<!--This XML file contains the gestures of the database.-->
<Gestures>
  <Gesture>
    <ID>0</ID>
    <NAME>Dislike</NAME>
    <SEMANTIC>Dislike</SEMANTIC>
  </Gesture>
  <Gesture>
    <ID>1</ID>
    <NAME>FullScreen</NAME>
    <SEMANTIC>FullS</SEMANTIC>
  </Gesture>
  <Gesture>
    <ID>2</ID>
    <NAME>Like</NAME>
    <SEMANTIC>Like</SEMANTIC>
  </Gesture>
  <Gesture>
    <ID>3</ID>
    <NAME>NextVideo</NAME>
    <SEMANTIC>NextV</SEMANTIC>
  </Gesture>
  <Gesture>
    <ID>4</ID>
    <NAME>NormalScreen</NAME>
    <SEMANTIC>NormalS</SEMANTIC>
  </Gesture>
  <Gesture>
    <ID>5</ID>
    <NAME>PreviousVideo</NAME>
    <SEMANTIC>PreviousV</SEMANTIC>
  </Gesture>
  <Gesture>
    <ID>6</ID>
    <NAME>SlideDown</NAME>
    <SEMANTIC>SlideD</SEMANTIC>
  </Gesture>
  <Gesture>
    <ID>7</ID>
    <NAME>SlideUP</NAME>
    <SEMANTIC>SlideUP</SEMANTIC>
  </Gesture>
  <Gesture>
    <ID>8</ID>
    <NAME>VolumeDown</NAME>
    <SEMANTIC>VolumeD</SEMANTIC>
  </Gesture>
  <Gesture>
    <ID>9</ID>
    <NAME>VolumeUp</NAME>
    <SEMANTIC>VolumeU</SEMANTIC>
  </Gesture>
</Gestures>